pylawson/__init__.py
pylawson/exceptions.py
pylawson/pylawson.py
pylawson/client/__init__.py
pylawson/client/base_session.py
pylawson/client/ms_samlpr.py
pylawson/client/sec_api.py
pylawson-0.3.dist-info/licenses/LICENSE
pylawson-0.3.dist-info/METADATA
pylawson-0.3.dist-info/WHEEL
pylawson-0.3.dist-info/top_level.txt
pylawson-0.3.dist-info/RECORD
