Metadata-Version: 2.4
Name: pylawson
Version: 0.3
Summary: Infor Lawson IOS API Wrapper
Author-email: Joe Carey <joe@accountingdatasolutions.com>
License-Expression: Apache-2.0
Project-URL: Homepage, https://git.accountingdatasolutions.com/indepndnt/pylawson
Keywords: infor,lawson,erp
License-File: LICENSE
Requires-Dist: beautifulsoup4
Requires-Dist: requests
Provides-Extra: sec-api
Requires-Dist: clr; extra == "sec-api"
Dynamic: license-file
